fhir_helpers/__init__.py
fhir_helpers/py.typed
fhir_helpers/utils.py
fhir_helpers/version.py
fhir_helpers/models/__init__.py
fhir_helpers/models/codeable_concept.py
fhir_helpers/models/coding.py
fhir_helpers/models/risk_assessment.py
fhir_helpers/resources/__init__.py
fhir_helpers/resources/allergy_intolerance.py
fhir_helpers/resources/codeable_concept.py
fhir_helpers/resources/coding.py
fhir_helpers/resources/condition.py
fhir_helpers/resources/encounter.py
fhir_helpers/resources/human_name.py
fhir_helpers/resources/immunization.py
fhir_helpers/resources/lpr.py
fhir_helpers/resources/medication_dispense.py
fhir_helpers/resources/medication_request.py
fhir_helpers/resources/observation.py
fhir_helpers/resources/observation_component.py
fhir_helpers/resources/observation_value.py
fhir_helpers/resources/patient.py
fhir_helpers/resources/period.py
fhir_helpers/resources/practitioner.py
fhir_helpers/resources/procedure.py
fhir_helpers/resources/quantity.py
fhir_helpers/resources/reference.py
fhir_helpers/resources/resource.py
fhir_helpers/resources/resource_list.py
fhir_helpers/rules_engine/__init__.py
fhir_helpers/rules_engine/nodes.py
fhir_helpers/rules_engine/rules_engine.py
fhir_helpers-0.12.0.dist-info/LICENSE.md
fhir_helpers-0.12.0.dist-info/METADATA
fhir_helpers-0.12.0.dist-info/WHEEL
fhir_helpers-0.12.0.dist-info/top_level.txt
fhir_helpers-0.12.0.dist-info/RECORD
