Metadata-Version: 2.1
Name: fhir-helpers
Version: 0.12.0
Summary: FHIR Helpers
Author: Anthem Inc
License: Apache
Keywords: FHIR
Requires-Python: >=3.8
License-File: LICENSE.md
Requires-Dist: python-dateutil
Requires-Dist: fhir-types
Provides-Extra: protobuf
Requires-Dist: google-fhir ; extra == 'protobuf'
